hyena.py
hyena_py-0.0.2.dist-info/LICENSE
hyena_py-0.0.2.dist-info/WHEEL
hyena_py-0.0.2.dist-info/METADATA
hyena_py-0.0.2.dist-info/RECORD
